MANIFEST.in
README.rst
setup.py
cookie_message/__init__.py
cookie_message/middleware.py
cookie_message/models.py
cookie_message/templates/cookies/message.html
django_cookie_message.egg-info/PKG-INFO
django_cookie_message.egg-info/SOURCES.txt
django_cookie_message.egg-info/dependency_links.txt
django_cookie_message.egg-info/not-zip-safe
django_cookie_message.egg-info/top_level.txt