Metadata-Version: 1.0
Name: django-cookie-message
Version: 0.1
Summary: UNKNOWN
Home-page: https://github.com/incuna/django-cookie-message/
Author: Incuna Ltd
Author-email: admin@incuna.com
License: UNKNOWN
Platform: UNKNOWN
